Processor.v
module fwdUnit (
    input [7:0] DATA2,
    output [7:0] RESULT);
    
    assign #1 RESULT = DATA2;
endmodule

module addUnit (
    input  [7:0] DATA1,
    input  [7:0] DATA2,
    output [7:0] RESULT);

    assign #2 RESULT = DATA1 + DATA2;
endmodule

module andUnit (
    input  [7:0] DATA1,
    input  [7:0] DATA2,
    output [7:0] RESULT);

    assign #1 RESULT = DATA1 & DATA2;
endmodule

module orUnit (
    input  [7:0] DATA1,
    input  [7:0] DATA2,
    output [7:0] RESULT);

    assign #1 RESULT = DATA1 | DATA2;
endmodule

module mulUnit (
    input  signed [7:0] DATA1,      // Multiplicand
    input  signed [7:0] DATA2,      // Multiplier
    input ENABLE,
    output reg signed [7:0] RESULT // Final 16-bit signed product
    );

    integer i;
    reg [15:0] temp1, temp2;

    always @(*) begin
        temp1 = 16'b0;
        temp2 = {8'b0, DATA1};

        for (i = 0; i < 8; i = i + 1) begin
            if (DATA2[i]) temp1 = temp1 + temp2;
            temp2 = {temp2, 1'b0};
        end

        RESULT = ENABLE ? temp1[7:0] : 8'b0; 
    end
endmodule

module shifterUnit (    
    input  [7:0] DATA1,     // 8-bit input DATA1
    input  [7:0] DATA2,     // 8-bit input DATA2
    input  ENABLE,
    output reg [7:0] RESULT // 8-bit output RESULT
    );

    integer i;
    reg sign;

    always @(*) begin
        if (ENABLE) begin
        RESULT = DATA1;
        sign = DATA1[7];
        for (i = 0; i < DATA2[3:0]; i = i + 1) begin
            case (DATA2[5:4])
                2'b00: RESULT = {RESULT[6:0], 1'b0};          // Logical shift left (sll)
                2'b01: RESULT = {1'b0, RESULT[7:1]};          // Logical shift right (srl)
                2'b10: RESULT = {sign, RESULT[7:1]};          // Arithmetic shift right (sra)
                2'b11: RESULT = {RESULT[0], RESULT[7:1]};     // Rotate right (ror)
            endcase
        end
        //#4; // Delay for shifting
        end 
        else begin
            RESULT = 8'B0;
        end
    end
endmodule

module aluUnit(
    input [7:0] DATA1,        // 8-bit input DATA1
    input [7:0] DATA2,        // 8-bit input DATA2
    input [2:0] ALUOP,     // 3-bit selector to choose operation
    output reg [7:0] RESULT,   // 8-bit output RESULT
    output reg ZERO
    );

    wire [7:0] sum, andOut, orOut, fwdOut, mulOut, shiftOut;
    wire SHIFT_E;

    assign SHIFT_E = (ALUOP == 3'b101) ? 1'b1: 1'b0;
    assign MUL_E   = (ALUOP == 3'b100) ? 1'b1: 1'b0;

    fwdUnit     u0 (.RESULT(fwdOut)  , .DATA2(DATA2));
    addUnit     u1 (.RESULT(sum)     , .DATA1(DATA1), .DATA2(DATA2));
    andUnit     u3 (.RESULT(andOut)  , .DATA1(DATA1), .DATA2(DATA2));
    orUnit      u4 (.RESULT(orOut)   , .DATA1(DATA1), .DATA2(DATA2));
    mulUnit     u5 (.RESULT(mulOut)  , .DATA1(DATA1), .DATA2(DATA2), .ENABLE(MUL_E));
    shifterUnit u6 (.RESULT(shiftOut), .DATA1(DATA1), .DATA2(DATA2), .ENABLE(SHIFT_E));
    
    always @(*) begin
        case (ALUOP)
            3'b000: RESULT = fwdOut;    
            3'b001: RESULT = sum;      
            3'b010: RESULT = andOut;  
            3'b011: RESULT = orOut;
            3'b100: RESULT = mulOut;
            3'b101: RESULT = shiftOut;                
            default: RESULT = 8'b0; 
        endcase

        // Sets the ZERO flag if the result is zero
        ZERO = (sum == 0) ? 1'b1: 1'b0;  
    end
endmodule

// registerFile.v - Register File module
// This module implements a register file with read and write capabilities.
// It has 8 registers, each 8 bits wide.

module reg_file(
    input [7:0] INDATA,             // Data to write
    input [2:0] INADDRESS,          // Address of register to write
    input [2:0] OUT1ADDRESS,        // Address of register to read (port 1)
    input [2:0] OUT2ADDRESS,        // Address of register to read (port 2)
    output reg [7:0] OUT1DATA,      // Data output from register (port 1)
    output reg [7:0] OUT2DATA,      // Data output from register (port 2)
    input CLK,                      // Clock signal
    input RESET,                    // Reset signal (active high)
    input  WRITE                    // Write enable signal
    );

    reg [7:0] reg_array [0:7]; 

    // Expose registers as wires for waveform dumping
        wire [7:0] r0 = reg_array[0];
        wire [7:0] r1 = reg_array[1];
        wire [7:0] r2 = reg_array[2];
        wire [7:0] r3 = reg_array[3];
        wire [7:0] r4 = reg_array[4];
        wire [7:0] r5 = reg_array[5];
        wire [7:0] r6 = reg_array[6];
        wire [7:0] r7 = reg_array[7];

    always @(*) begin
        OUT1DATA <= #2 reg_array[OUT1ADDRESS];  // Output data from register reg1
        OUT2DATA <= #2 reg_array[OUT2ADDRESS];  // Output data from register reg2
    end

    // On write enable, write data to specified register on positive edge of Clock
    always @(posedge CLK) begin
        if(WRITE == 1'b1  &&  RESET == 1'b0) begin 
            reg_array[INADDRESS] <= #1 INDATA;
        end
    end

    // On reset, clear all registers
    integer counter;             
    always @(posedge CLK) begin
        if(RESET == 1'b1) begin
            for(counter = 0; counter < 8; counter = counter + 1) begin
                reg_array[counter] <= #1 8'b00000000;
            end
        end
    end
endmodule

module control_unit(
    input [7:0] OPCODE,
    output reg WRITE_ENABLE,
    output reg [2:0] ALUOP,
    output reg SIGN_CONTROL,
    output reg OPERAND_CONTROL,
    output reg [1:0] BRANCH_CONTROL,
    output reg JUMP_CONTROL
    );

    // ALU operation codes
    localparam OP_LOADI = 8'b00000000;
    localparam OP_MOV   = 8'b00000001;
    localparam OP_ADD   = 8'b00000010;
    localparam OP_SUB   = 8'b00000011;
    localparam OP_AND   = 8'b00000100;
    localparam OP_OR    = 8'b00000101;
    localparam OP_J     = 8'b00000110;
    localparam OP_BEQ   = 8'b00000111;
    
    localparam OP_MUL   = 8'b00001000;
    localparam OP_SHIFT = 8'b00001001;
    localparam OP_BNE   = 8'b00001010;

    always @(OPCODE) begin 
        ALUOP <= #1 (OPCODE == OP_ADD)   ? 3'b001 :
                (OPCODE == OP_SUB)   ? 3'b001 :
                (OPCODE == OP_AND)   ? 3'b010 :
                (OPCODE == OP_OR)    ? 3'b011 :
                (OPCODE == OP_MOV)   ? 3'b000 :
                (OPCODE == OP_LOADI) ? 3'b000 :
                (OPCODE == OP_MUL)   ? 3'b100 :
                (OPCODE == OP_SHIFT) ? 3'b101 :
                3'b000;

        BRANCH_CONTROL   = (OPCODE == OP_BEQ)   ? 2'b01 : 
                           (OPCODE == OP_BNE)   ? 2'b10 : 2'b00;

        JUMP_CONTROL     = (OPCODE == OP_J)     ? 1'b1 : 1'b0;

        SIGN_CONTROL     = (OPCODE == OP_SUB || OPCODE == OP_BEQ || OPCODE == OP_BNE)   ? 1'b1 : 1'b0;

        OPERAND_CONTROL  = (OPCODE == OP_LOADI || OPCODE == OP_SHIFT) ? 1'b1 : 1'b0;

        WRITE_ENABLE  = (OPCODE == OP_LOADI || OPCODE == OP_MOV || OPCODE == OP_ADD ||
                    OPCODE == OP_SUB || OPCODE == OP_AND || OPCODE == OP_OR ||
                    OPCODE == OP_MUL || OPCODE == OP_SHIFT) ? 1'b1 : 1'b0;
    end
endmodule

module ProgramCounter(
    input CLK, RESET,
    input      [31:0] PC_IN,
    output reg [31:0] PC_OUT
    );

    always @(posedge CLK or posedge RESET) begin 
        if (RESET) begin
            PC_OUT <= #1 32'b0;
        end
        else begin
            PC_OUT <= #1 PC_IN;
        end
    end
endmodule

module pcIncrementer (
    input [31:0] PC_IN,
    input [7:0]  BRANCH_ADDRESS,
    input [1:0]  BRANCH, 
    input        JUMP, ZERO,
    output reg [31:0] PC_OUT
    );

    reg [31:0] PC;
    reg [31:0] offset;

    always @(*) begin
        PC <= #1 PC_IN + 32'd4;
 
        offset <= #2 PC + {{22{BRANCH_ADDRESS[7]}}, BRANCH_ADDRESS, 2'b00}; 

        PC_OUT =    JUMP ? offset : 
                    (BRANCH == 2'b01 && ZERO) ? offset : 
                    (BRANCH == 2'b10 && !ZERO) ? offset : PC;
    end
endmodule

module CPU(
    input [31:0] INSTRUCTION,
    input CLK, RESET, 
    output wire [31:0] PC_OUT
    );

    wire [7:0] OPERAND1, OPERAND2, ALURESULT;
    wire [2:0] ALUOP;
    wire REG_WRITE_ENABLE;
    wire SIGN_CONTROL, OPERAND_CONTROL;

    wire [1:0] BRANCH_CONTROL;
    wire JUMP_CONTROL;
    wire ZERO_FLAG;              // to control the gates for beq instruction
    wire [31:0] PC_IN;

    ProgramCounter u_pc (
        .CLK(CLK),
        .RESET(RESET),
        .PC_IN(PC_IN),
        .PC_OUT(PC_OUT)
    );

    pcIncrementer u_pcIn (
        .PC_IN(PC_OUT),
        .BRANCH_ADDRESS(INSTRUCTION[15:8]),
        .BRANCH(BRANCH_CONTROL), 
        .JUMP(JUMP_CONTROL), 
        .ZERO(ZERO_FLAG),
        .PC_OUT(PC_IN)
    );
    
    control_unit u_control (
        .OPCODE (INSTRUCTION[7:0]),
        .WRITE_ENABLE(REG_WRITE_ENABLE),
        .ALUOP(ALUOP),
        .SIGN_CONTROL(SIGN_CONTROL),
        .OPERAND_CONTROL(OPERAND_CONTROL),
        .BRANCH_CONTROL(BRANCH_CONTROL),
        .JUMP_CONTROL(JUMP_CONTROL)
    );

    reg_file u_regfile (
        .INDATA(ALURESULT),
        .INADDRESS(INSTRUCTION[10:8]),
        .OUT1ADDRESS(INSTRUCTION[18:16]),
        .OUT2ADDRESS(INSTRUCTION[26:24]),
        .OUT1DATA(OPERAND1),
        .OUT2DATA(OPERAND2),
        .WRITE(REG_WRITE_ENABLE),
        .CLK(CLK),
        .RESET(RESET)
    ); 

    reg [7:0] ALU_IN_DATA1, ALU_IN_DATA2;

    always @(*) begin
        ALU_IN_DATA1 = OPERAND1;
        if (OPERAND_CONTROL) begin
            ALU_IN_DATA2 = INSTRUCTION[31:24];
        end
        else begin
            if (SIGN_CONTROL) begin
                ALU_IN_DATA2 <= #2 (~OPERAND2 + 8'b1);
            end
            else begin
                ALU_IN_DATA2 = OPERAND2;
            end
        end
    end    

    aluUnit u_alu (
        .DATA1(ALU_IN_DATA1),
        .DATA2(ALU_IN_DATA2),
        .ALUOP(ALUOP),
        .RESULT(ALURESULT),
        .ZERO(ZERO_FLAG)
    );
endmodule

cpu_tb.v
module cpu_tb;

    reg CLK, RESET;
    wire [31:0] PC;
    reg [31:0] INSTRUCTION;
    reg [7:0] instr_mem [0:1023];  // 1KB instruction memory
    integer i;

    // Instantiate the CPU
    CPU mycpu (
        .PC_OUT(PC),
        .INSTRUCTION(INSTRUCTION),
        .CLK(CLK),
        .RESET(RESET)
    );

    // Clock generation (period = 8 time units)
    always #4 CLK = ~CLK;

    // Instruction fetch on PC change
    always @(PC) begin
        // Instruction memory should be word-addressable in steps of 4
        INSTRUCTION <= #2 {
            instr_mem[PC + 0],
            instr_mem[PC + 1],
            instr_mem[PC + 2],
            instr_mem[PC + 3]
        };
        $display("->    Cycle %0d: PC = %0d, Instruction = %b", i, PC, INSTRUCTION);
    end

    initial begin
        // Load instruction memory from file
        $readmemb("instr_mem.mem", instr_mem);

        // Optional: Display initial memory (commented)
        /*
        $display("Instruction Memory Contents (First 32 Bytes):");
        for (i = 0; i < 32; i = i + 1) begin
            $display("addr[%0d] = %b", i, instr_mem[i]);
        end
        */

        // Initialize waveform dump
        $dumpfile("cpu_wavedata.vcd");
        $dumpvars(0, cpu_tb);
        /*
        $dumpvars(1, cpu_tb.mycpu.u_regfile.r0);
        $dumpvars(1, cpu_tb.mycpu.u_regfile.r1);
        $dumpvars(1, cpu_tb.mycpu.u_regfile.r2);
        $dumpvars(1, cpu_tb.mycpu.u_regfile.r3);
        $dumpvars(1, cpu_tb.mycpu.u_regfile.r4);
        $dumpvars(1, cpu_tb.mycpu.u_regfile.r5);
        $dumpvars(1, cpu_tb.mycpu.u_regfile.r6);
        $dumpvars(1, cpu_tb.mycpu.u_regfile.r7);
        */

        // Initialize signals
        CLK = 0;
        RESET = 1;
        #8; // Wait 8 time units for RESET to propagate
        @(posedge CLK);  // Sync with clock
        RESET = 0;

        // Run for 4 cycles
        for (i = 0; i < 20; i = i + 1) begin
            @(posedge CLK);
        end

        #10 $finish;
    end

endmodule

cpu_wavedata.vcd
$date
	Wed Jun 18 02:38:44 2025
$end
$version
	Icarus Verilog
$end
$timescale
	1s
$end
$scope module cpu_tb $end
$var wire 32 ! PC [31:0] $end
$var reg 1 " CLK $end
$var reg 32 # INSTRUCTION [31:0] $end
$var reg 1 $ RESET $end
$var integer 32 % i [31:0] $end
$scope module mycpu $end
$var wire 1 " CLK $end
$var wire 32 & INSTRUCTION [31:0] $end
$var wire 1 $ RESET $end
$var wire 1 ' ZERO_FLAG $end
$var wire 1 ( SIGN_CONTROL $end
$var wire 1 ) REG_WRITE_ENABLE $end
$var wire 32 * PC_OUT [31:0] $end
$var wire 32 + PC_IN [31:0] $end
$var wire 1 , OPERAND_CONTROL $end
$var wire 8 - OPERAND2 [7:0] $end
$var wire 8 . OPERAND1 [7:0] $end
$var wire 1 / JUMP_CONTROL $end
$var wire 2 0 BRANCH_CONTROL [1:0] $end
$var wire 8 1 ALURESULT [7:0] $end
$var wire 3 2 ALUOP [2:0] $end
$var reg 8 3 ALU_IN_DATA1 [7:0] $end
$var reg 8 4 ALU_IN_DATA2 [7:0] $end
$scope module u_alu $end
$var wire 8 5 DATA1 [7:0] $end
$var wire 8 6 DATA2 [7:0] $end
$var wire 8 7 sum [7:0] $end
$var wire 8 8 shiftOut [7:0] $end
$var wire 8 9 orOut [7:0] $end
$var wire 8 : mulOut [7:0] $end
$var wire 8 ; fwdOut [7:0] $end
$var wire 8 < andOut [7:0] $end
$var wire 1 = SHIFT_E $end
$var wire 1 > MUL_E $end
$var wire 3 ? ALUOP [2:0] $end
$var reg 8 @ RESULT [7:0] $end
$var reg 1 ' ZERO $end
$scope module u0 $end
$var wire 8 A DATA2 [7:0] $end
$var wire 8 B RESULT [7:0] $end
$upscope $end
$scope module u1 $end
$var wire 8 C DATA1 [7:0] $end
$var wire 8 D DATA2 [7:0] $end
$var wire 8 E RESULT [7:0] $end
$upscope $end
$scope module u3 $end
$var wire 8 F DATA1 [7:0] $end
$var wire 8 G DATA2 [7:0] $end
$var wire 8 H RESULT [7:0] $end
$upscope $end
$scope module u4 $end
$var wire 8 I DATA1 [7:0] $end
$var wire 8 J DATA2 [7:0] $end
$var wire 8 K RESULT [7:0] $end
$upscope $end
$scope module u5 $end
$var wire 8 L DATA1 [7:0] $end
$var wire 8 M DATA2 [7:0] $end
$var wire 1 > ENABLE $end
$var reg 8 N RESULT [7:0] $end
$var reg 16 O temp1 [15:0] $end
$var reg 16 P temp2 [15:0] $end
$var integer 32 Q i [31:0] $end
$upscope $end
$scope module u6 $end
$var wire 8 R DATA1 [7:0] $end
$var wire 8 S DATA2 [7:0] $end
$var wire 1 = ENABLE $end
$var reg 8 T RESULT [7:0] $end
$var reg 1 U sign $end
$var integer 32 V i [31:0] $end
$upscope $end
$upscope $end
$scope module u_control $end
$var wire 8 W OPCODE [7:0] $end
$var reg 3 X ALUOP [2:0] $end
$var reg 2 Y BRANCH_CONTROL [1:0] $end
$var reg 1 / JUMP_CONTROL $end
$var reg 1 , OPERAND_CONTROL $end
$var reg 1 ( SIGN_CONTROL $end
$var reg 1 ) WRITE_ENABLE $end
$upscope $end
$scope module u_pc $end
$var wire 1 " CLK $end
$var wire 1 $ RESET $end
$var wire 32 Z PC_IN [31:0] $end
$var reg 32 [ PC_OUT [31:0] $end
$upscope $end
$scope module u_pcIn $end
$var wire 2 \ BRANCH [1:0] $end
$var wire 8 ] BRANCH_ADDRESS [7:0] $end
$var wire 1 / JUMP $end
$var wire 32 ^ PC_IN [31:0] $end
$var wire 1 ' ZERO $end
$var reg 32 _ PC [31:0] $end
$var reg 32 ` PC_OUT [31:0] $end
$var reg 32 a offset [31:0] $end
$upscope $end
$scope module u_regfile $end
$var wire 1 " CLK $end
$var wire 3 b INADDRESS [2:0] $end
$var wire 8 c INDATA [7:0] $end
$var wire 3 d OUT1ADDRESS [2:0] $end
$var wire 3 e OUT2ADDRESS [2:0] $end
$var wire 1 $ RESET $end
$var wire 1 ) WRITE $end
$var wire 8 f r0 [7:0] $end
$var wire 8 g r1 [7:0] $end
$var wire 8 h r2 [7:0] $end
$var wire 8 i r3 [7:0] $end
$var wire 8 j r4 [7:0] $end
$var wire 8 k r5 [7:0] $end
$var wire 8 l r6 [7:0] $end
$var wire 8 m r7 [7:0] $end
$var reg 8 n OUT1DATA [7:0] $end
$var reg 8 o OUT2DATA [7:0] $end
$var integer 32 p counter [31:0] $end
$upscope $end
$upscope $end
$upscope $end
$enddefinitions $end
#0
$dumpvars
bx p
bx o
bx n
bx m
bx l
bx k
bx j
bx i
bx h
bx g
bx f
bx e
bx d
b0 c
bx b
bx a
bx `
bx _
bx ^
bx ]
bx \
bx [
bx Z
bx Y
bx X
bx W
bx V
xU
b0 T
bx S
bx R
b1000 Q
bx00000000 P
b0 O
b0 N
bx M
bx L
bx K
bx J
bx I
bx H
bx G
bx F
bx E
bx D
bx C
bx B
bx A
b0 @
bx ?
x>
x=
bx <
bx ;
b0 :
bx 9
b0 8
bx 7
bx 6
bx 5
bx 4
bx 3
bx 2
b0 1
bx 0
x/
bx .
bx -
x,
bx +
bx *
x)
x(
x'
bx &
bx %
1$
bx #
0"
bx !
$end
#1
b0 !
b0 *
b0 [
b0 ^
#2
b100 _
#3
bx :
bx N
bx O
b1000 Q
bx00000000 P
b101 4
b101 6
b101 A
b101 D
b101 G
b101 J
b101 M
b101 S
b100 +
b100 Z
b100 `
1)
1,
0(
0/
b0 0
b0 Y
b0 \
b100 ]
b0 W
b100 b
b0 d
b101 e
b101000000000000010000000000 #
b101000000000000010000000000 &
#4
b0 :
b0 N
b1000 Q
bx00000000 P
bx O
0>
0=
b101 1
b101 @
b101 c
b0 2
b0 ?
b0 X
b1000 p
b0x0x <
b0x0x H
bx1x1 9
bx1x1 K
b101 ;
b101 B
1"
#5
b0 m
b0 l
b0 k
b0 j
b0 i
b0 h
b0 g
b0 f
b10100 a
#7
b1000 Q
b0 P
b0 O
b0 3
b0 5
b0 C
b0 F
b0 I
b0 L
b0 R
b0 -
b0 o
b0 .
b0 n
#8
b0 <
b0 H
b101 9
b101 K
0"
#9
0'
b101 7
b101 E
#12
b0 %
0$
1"
#13
b100 !
b100 *
b100 [
b100 ^
b101 j
#14
b1000 +
b1000 Z
b1000 `
b1000 _
#15
b1000 Q
b1001 4
b1001 6
b1001 A
b1001 D
b1001 G
b1001 J
b1001 M
b1001 S
b10 ]
b10 b
b1 e
b1001000000000000001000000000 #
b1001000000000000001000000000 &
#16
b11000 a
b1001 1
b1001 @
b1001 c
b1001 9
b1001 K
b1001 ;
b1001 B
0"
#17
b10000 a
b1001 7
b1001 E
#20
b1 %
1"
#21
b1000 !
b1000 *
b1000 [
b1000 ^
b1001 h
#22
b1100 +
b1100 Z
b1100 `
b1100 _
#23
b1000 Q
0,
b0 4
b0 6
b0 A
b0 D
b0 G
b0 J
b0 M
b0 S
b110 ]
b10 W
b110 b
b100 d
b10 e
b10000001000000011000000010 #
b10000001000000011000000010 &
#24
b1 2
b1 ?
b1 X
b10100 a
b1001 1
b1001 @
b1001 c
b0 9
b0 K
b0 ;
b0 B
0"
#25
b101101 O
b1000 Q
b10100000000 P
b1001 4
b1001 6
b1001 A
b1001 D
b1001 G
b1001 J
b1001 M
b1001 S
b101 3
b101 5
b101 C
b101 F
b101 I
b101 L
b101 R
b100100 a
b1001 -
b1001 o
b101 .
b101 n
1'
b0 1
b0 @
b0 c
b0 7
b0 E
#26
b1 <
b1 H
b1101 9
b1101 K
b1001 ;
b1001 B
#27
0'
b1110 1
b1110 @
b1110 c
b1110 7
b1110 E
#28
b10 %
1"
#29
b1100 !
b1100 *
b1100 [
b1100 ^
b1110 l
#30
b10000 +
b10000 Z
b10000 `
b10000 _
#31
b0 ]
b1 W
b0 b
b0 d
b110 e
b110000000000000000000000001 #
b110000000000000000000000001 &
#32
b1001 1
b1001 @
b1001 c
b0 2
b0 ?
b0 X
b101000 a
0"
#33
b1000 Q
b0 P
b0 O
b1110 4
b1110 6
b1110 A
b1110 D
b1110 G
b1110 J
b1110 M
b1110 S
b0 3
b0 5
b0 C
b0 F
b0 I
b0 L
b0 R
b10000 a
b1110 -
b1110 o
b0 .
b0 n
#34
b1110 1
b1110 @
b1110 c
b0 <
b0 H
b1110 9
b1110 K
b1110 ;
b1110 B
#36
b11 %
1"
#37
b10000 !
b10000 *
b10000 [
b10000 ^
b1110 f
#38
b10100 +
b10100 Z
b10100 `
b10100 _
#39
b1 4
b1 6
b1 A
b1 D
b1 G
b1 J
b1 M
b1 S
1,
b1110 O
b1000 Q
b111000000000 P
b1 ]
b0 W
b1 b
b1 e
b1110 3
b1110 5
b1110 C
b1110 F
b1110 I
b1110 L
b1110 R
b1000000000000000100000000 #
b1000000000000000100000000 &
b1110 .
b1110 n
#40
b10100 a
b1 1
b1 @
b1 c
b1111 9
b1111 K
b1 ;
b1 B
0"
#41
b11000 a
b0 -
b0 o
b1111 7
b1111 E
#44
b100 %
1"
#45
b10100 !
b10100 *
b10100 [
b10100 ^
b1 g
#46
b11000 +
b11000 Z
b11000 `
b11000 _
#47
0,
b10 ]
b10 W
b10 b
b10 d
b1000000100000001000000010 #
b1000000100000001000000010 &
b1 -
b1 o
#48
b1111 1
b1111 @
b1111 c
b1 2
b1 ?
b1 X
b11100 a
0"
#49
b1000 Q
b100100000000 P
b1001 O
b1001 3
b1001 5
b1001 C
b1001 F
b1001 I
b1001 L
b1001 R
b100000 a
b1001 .
b1001 n
#50
b1 <
b1 H
b1001 9
b1001 K
#51
b1010 1
b1010 @
b1010 c
b1010 7
b1010 E
#52
b101 %
1"
#53
b11000 !
b11000 *
b11000 [
b11000 ^
b1010 h
#54
b11100 +
b11100 Z
b11100 `
b11100 _
#55
b100000 +
b100000 Z
b100000 `
0)
1/
b1000 Q
b101000000000 P
b1010 O
b110 W
b0 d
b0 e
b1010 3
b1010 5
b1010 C
b1010 F
b1010 I
b1010 L
b1010 R
b1000000110 #
b1000000110 &
b1010 .
b1010 n
#56
b1 1
b1 @
b1 c
b100100 +
b100100 Z
b100100 `
b0 2
b0 ?
b0 X
b100100 a
b0 <
b0 H
b1011 9
b1011 K
0"
#57
b1000 Q
b111000000000 P
b11000100 O
b1110 4
b1110 6
b1110 A
b1110 D
b1110 G
b1110 J
b1110 M
b1110 S
b1110 3
b1110 5
b1110 C
b1110 F
b1110 I
b1110 L
b1110 R
b1110 -
b1110 o
b1110 .
b1110 n
b1011 7
b1011 E
#58
b1110 1
b1110 @
b1110 c
b1110 <
b1110 H
b1110 9
b1110 K
b1110 ;
b1110 B
#59
b11100 7
b11100 E
#60
b110 %
1"
#61
b100100 !
b100100 *
b100100 [
b100100 ^
#62
b101000 _
#63
b1000 Q
b111000000000 P
b101111101100 O
b11011010 4
b11011010 6
b11011010 A
b11011010 D
b11011010 G
b11011010 J
b11011010 M
b11011010 S
b101000 +
b101000 Z
b101000 `
1)
1,
0/
b100 ]
b0 W
b100 b
b10 e
b11011010000000000000010000000000 #
b11011010000000000000010000000000 &
#64
b110000 a
b11011010 1
b11011010 @
b11011010 c
b1010 <
b1010 H
b11011110 9
b11011110 K
b11011010 ;
b11011010 B
0"
#65
b111000 a
b1010 -
b1010 o
b11101000 7
b11101000 E
#68
b111 %
1"
#69
b101000 !
b101000 *
b101000 [
b101000 ^
b11011010 j
#70
b101100 +
b101100 Z
b101100 `
b101100 _
#71
b1000 Q
b111000000000 P
b1010111100 O
b110010 4
b110010 6
b110010 A
b110010 D
b110010 G
b110010 J
b110010 M
b110010 S
b111 ]
b1001 W
b111 b
b100 d
b110010000001000000011100001001 #
b110010000001000000011100001001 &
#72
b10 V
0U
b10000011 8
b10000011 T
1=
b101 2
b101 ?
b101 X
b111100 a
b10000011 1
b10000011 @
b10000011 c
b10 <
b10 H
b111110 9
b111110 K
b110010 ;
b110010 B
0"
#73
b10110110 1
b10110110 @
b10110110 c
b1000 Q
b1101101000000000 P
b10101010010100 O
b10 V
1U
b10110110 8
b10110110 T
b11011010 3
b11011010 5
b11011010 C
b11011010 F
b11011010 I
b11011010 L
b11011010 R
b1001000 a
b11011010 .
b11011010 n
b1000000 7
b1000000 E
#74
b10010 <
b10010 H
b11111010 9
b11111010 K
#75
b1100 7
b1100 E
#76
b1000 %
1"
#77
b101100 !
b101100 *
b101100 [
b101100 ^
b10110110 m
#78
b110000 +
b110000 Z
b110000 `
b110000 _
#79
b0 1
b0 @
b0 c
b1000 Q
b1101101000000000 P
b100010000100 O
b1010 V
b0 8
b0 T
b0xxxx000 +
b0xxxx000 Z
b0xxxx000 `
x)
x,
x(
x/
bx 0
bx Y
bx \
b1010 4
b1010 6
b1010 A
b1010 D
b1010 G
b1010 J
b1010 M
b1010 S
bx ]
bx W
bx b
bx d
bx e
bx #
bx &
#80
bx0000x00 :
bx0000x00 N
b1000 Q
b1101101000000000 P
b100010000100 O
x>
x=
b0xxxxx00 +
b0xxxxx00 Z
b0xxxxx00 `
bx 2
bx ?
bx X
b1001100 a
b1010 <
b1010 H
b11011010 9
b11011010 K
b1010 ;
b1010 B
0"
#81
b0 :
b0 N
b1000 Q
bx00000000 P
b0 O
bx +
bx Z
bx `
bx 4
bx 6
bx A
bx D
bx G
bx J
bx M
bx S
bx 3
bx 5
bx C
bx F
bx I
bx L
bx R
bx a
bx -
bx o
bx .
bx n
b11100100 7
b11100100 E
#82
bx <
bx H
bx 9
bx K
bx ;
bx B
#83
x'
bx 7
bx E
#84
b1001 %
1"
#85
bx !
bx *
bx [
bx ^
#86
bx _
#88
0"
#92
b1010 %
1"
#96
0"
#100
b1011 %
1"
#104
0"
#108
b1100 %
1"
#112
0"
#116
b1101 %
1"
#120
0"
#124
b1110 %
1"
#128
0"
#132
b1111 %
1"
#136
0"
#140
b10000 %
1"
#144
0"
#148
b10001 %
1"
#152
0"
#156
b10010 %
1"
#160
0"
#164
b10011 %
1"
#168
0"
#172
b10100 %
1"
