Processor.v
module fwdUnit (
    input [7:0] DATA2,
    output [7:0] RESULT);
    
    assign #1 RESULT = DATA2;
endmodule

module addUnit (
    input  [7:0] DATA1,
    input  [7:0] DATA2,
    output [7:0] RESULT);

    assign #2 RESULT = DATA1 + DATA2;
endmodule

module andUnit (
    input  [7:0] DATA1,
    input  [7:0] DATA2,
    output [7:0] RESULT);

    assign #1 RESULT = DATA1 & DATA2;
endmodule

module orUnit (
    input  [7:0] DATA1,
    input  [7:0] DATA2,
    output [7:0] RESULT);

    assign #1 RESULT = DATA1 | DATA2;
endmodule

module mulUnit (
    input  signed [7:0] DATA1,      // Multiplicand
    input  signed [7:0] DATA2,      // Multiplier
    output reg signed [7:0] RESULT // Final 16-bit signed product
    );

    reg signed [15:0] A;            // +Multiplicand shifted left
    reg signed [15:0] S;            // -Multiplicand shifted left
    reg signed [16:0] P;            // Product register: {A[7:0], Q[7:0], Q-1}
    integer i;

    always @(*) begin
            // Prepare multiplicand (+ and - versions)
            A = {DATA1, 8'b0};       // Left shift multiplicand by 8 bits
            S = {-DATA1, 8'b0};      // Left shift negative multiplicand

            // Initialize P with multiplier and extra Q-1 bit
            P = {8'b0, DATA2, 1'b0}; // {accumulator=0, multiplier, Q-1=0}

            // Booth's Algorithm Iteration
            for (i = 0; i < 8; i = i + 1) begin
                case (P[1:0])  // Examine Q0 and Q-1
                    2'b01: P[16:1] = P[16:1] + A; // Add A
                    2'b10: P[16:1] = P[16:1] + S; // Subtract A (add -A)
                    default: ;                   // No operation
                endcase

                // Arithmetic right shift of P (preserve sign)
                P = {P[16], P[16:1]};
            end

            // Assign final result (ignore Q-1 bit)
            #3 RESULT = P[8:1]; 
    end
endmodule

module shifterUnit (    
    input  [7:0] DATA1,     // 8-bit input DATA1
    input  [7:0] DATA2,     // 8-bit input DATA2
    output reg [7:0] RESULT // 8-bit output RESULT
    );

    integer i;
    reg sign;

    always @(*) begin
        RESULT = DATA1;
        sign = DATA1[7];
        for (i = 0; i < DATA2[3:0]; i = i + 1) begin
            case (DATA2[5:4])
                2'b00: RESULT = {RESULT[6:0], 1'b0};          // Logical shift left (sll)
                2'b01: RESULT = {1'b0, RESULT[7:1]};          // Logical shift right (srl)
                2'b10: RESULT = {sign, RESULT[7:1]};          // Arithmetic shift right (sra)
                2'b11: RESULT = {RESULT[0], RESULT[7:1]};     // Rotate right (ror)
            endcase
        end
        #4; // Delay for shifting
    end
endmodule

module aluUnit(
    input [7:0] DATA1,        // 8-bit input DATA1
    input [7:0] DATA2,        // 8-bit input DATA2
    input [2:0] ALUOP,     // 3-bit selector to choose operation
    output reg [7:0] RESULT,   // 8-bit output RESULT
    output reg ZERO
    );

    wire [7:0] sum, andOut, orOut, fwdOut, mulOut, shiftOut;

    fwdUnit     u0 (.RESULT(fwdOut)  , .DATA2(DATA2));
    addUnit     u1 (.RESULT(sum)     , .DATA1(DATA1), .DATA2(DATA2));
    andUnit     u3 (.RESULT(andOut)  , .DATA1(DATA1), .DATA2(DATA2));
    orUnit      u4 (.RESULT(orOut)   , .DATA1(DATA1), .DATA2(DATA2));
    mulUnit     u5 (.RESULT(mulOut)  , .DATA1(DATA1), .DATA2(DATA2));
    shifterUnit u6 (.RESULT(shiftOut), .DATA1(DATA1), .DATA2(DATA2));
    
    always @(*) begin
        case (ALUOP)
            3'b000: RESULT = fwdOut;    
            3'b001: RESULT = sum;      
            3'b010: RESULT = andOut;  
            3'b011: RESULT = orOut;
            3'b100: RESULT = mulOut;
            3'b101: RESULT = shiftOut;                
            default: RESULT = 8'b0; 
        endcase

        // Sets the ZERO flag if the result is zero
        ZERO = (sum == 0) ? 1'b1: 1'b0;  
    end
endmodule

// registerFile.v - Register File module
// This module implements a register file with read and write capabilities.
// It has 8 registers, each 8 bits wide.

module reg_file(
    input [7:0] INDATA,             // Data to write
    input [2:0] INADDRESS,          // Address of register to write
    input [2:0] OUT1ADDRESS,        // Address of register to read (port 1)
    input [2:0] OUT2ADDRESS,        // Address of register to read (port 2)
    output reg [7:0] OUT1DATA,      // Data output from register (port 1)
    output reg [7:0] OUT2DATA,      // Data output from register (port 2)
    input CLK,                      // Clock signal
    input RESET,                    // Reset signal (active high)
    input  WRITE                    // Write enable signal
    );

    reg [7:0] reg_array [0:7]; 

    // Expose registers as wires for waveform dumping
        wire [7:0] r0 = reg_array[0];
        wire [7:0] r1 = reg_array[1];
        wire [7:0] r2 = reg_array[2];
        wire [7:0] r3 = reg_array[3];
        wire [7:0] r4 = reg_array[4];
        wire [7:0] r5 = reg_array[5];
        wire [7:0] r6 = reg_array[6];
        wire [7:0] r7 = reg_array[7];

    always @(*) begin
        OUT1DATA <= #2 reg_array[OUT1ADDRESS];  // Output data from register reg1
        OUT2DATA <= #2 reg_array[OUT2ADDRESS];  // Output data from register reg2
    end

    // On write enable, write data to specified register on positive edge of Clock
    always @(posedge CLK) begin
        if(WRITE == 1'b1  &&  RESET == 1'b0) begin 
            reg_array[INADDRESS] <= #1 INDATA;
        end
    end

    // On reset, clear all registers
    integer counter;             
    always @(posedge CLK) begin
        if(RESET == 1'b1) begin
            for(counter = 0; counter < 8; counter = counter + 1) begin
                reg_array[counter] <= #1 8'b00000000;
            end
        end
    end
endmodule

module control_unit(
    input [7:0] OPCODE,
    output reg WRITE_ENABLE,
    output reg [2:0] ALUOP,
    output reg SIGN_CONTROL,
    output reg OPERAND_CONTROL,
    output reg [1:0] BRANCH_CONTROL,
    output reg JUMP_CONTROL
    );

    // ALU operation codes
    localparam OP_LOADI = 8'b00000000;
    localparam OP_MOV   = 8'b00000001;
    localparam OP_ADD   = 8'b00000010;
    localparam OP_SUB   = 8'b00000011;
    localparam OP_AND   = 8'b00000100;
    localparam OP_OR    = 8'b00000101;
    localparam OP_J     = 8'b00000110;
    localparam OP_BEQ   = 8'b00000111;
    
    localparam OP_MUL   = 8'b00001000;
    localparam OP_SHIFT = 8'b00001001;
    localparam OP_BNE   = 8'b00001010;

    always @(OPCODE) begin 
        ALUOP <= #1 (OPCODE == OP_ADD)   ? 3'b001 :
                (OPCODE == OP_SUB)   ? 3'b001 :
                (OPCODE == OP_AND)   ? 3'b010 :
                (OPCODE == OP_OR)    ? 3'b011 :
                (OPCODE == OP_MOV)   ? 3'b000 :
                (OPCODE == OP_LOADI) ? 3'b000 :
                (OPCODE == OP_MUL)   ? 3'b100 :
                (OPCODE == OP_SHIFT) ? 3'b101 :
                3'b000;

        BRANCH_CONTROL   = (OPCODE == OP_BEQ)   ? 2'b01 : 
                           (OPCODE == OP_BNE)   ? 2'b10 : 2'b00;

        JUMP_CONTROL     = (OPCODE == OP_J)     ? 1'b1 : 1'b0;

        SIGN_CONTROL     = (OPCODE == OP_SUB)   ? 1'b1 : 1'b0;

        OPERAND_CONTROL  = (OPCODE == OP_LOADI || OPCODE == OP_SHIFT) ? 1'b1 : 1'b0;

        WRITE_ENABLE  = (OPCODE == OP_LOADI || OPCODE == OP_MOV || OPCODE == OP_ADD ||
                    OPCODE == OP_SUB || OPCODE == OP_AND || OPCODE == OP_OR ||
                    OPCODE == OP_MUL || OPCODE == OP_SHIFT) ? 1'b1 : 1'b0;
    end
endmodule

module ProgramCounter(
    input CLK, RESET,
    input      [31:0] PC_IN,
    output reg [31:0] PC_OUT
    );

    always @(posedge CLK or posedge RESET) begin 
        if (RESET) begin
            PC_OUT <= #1 32'b0;
        end
        else begin
            PC_OUT <= #1 PC_IN;
        end
    end
endmodule

module pcIncrementer (
    input [31:0] PC_IN,
    input [7:0]  BRANCH_ADDRESS,
    input [1:0]  BRANCH, 
    input        JUMP, ZERO,
    output reg [31:0] PC_OUT
    );

    reg [31:0] PC;
    reg [31:0] offset;

    always @(*) begin
        PC <= #1 PC_IN + 32'd4;
 
        offset <= {{22{BRANCH_ADDRESS[7]}}, BRANCH_ADDRESS, 2'b00}; 
        offset <= #2 PC + offset;

        PC_OUT =    JUMP ? offset : 
                    (BRANCH == 2'b01 && ZERO) ? offset : 
                    (BRANCH == 2'b10 && !ZERO) ? offset : PC;
    end
endmodule

module CPU(
    input [31:0] INSTRUCTION,
    input CLK, RESET, 
    output wire [31:0] PC_OUT
    );

    wire [7:0] OPERAND1, OPERAND2, ALURESULT;
    wire [2:0] ALUOP;
    wire REG_WRITE_ENABLE;
    wire SIGN_CONTROL, OPERAND_CONTROL;

    wire [1:0] BRANCH_CONTROL;
    wire JUMP_CONTROL;
    wire ZERO_FLAG;              // to control the gates for beq instruction
    wire [31:0] PC_IN;

    ProgramCounter u_pc (
        .CLK(CLK),
        .RESET(RESET),
        .PC_IN(PC_IN),
        .PC_OUT(PC_OUT)
    );

    pcIncrementer u_pcIn (
        .PC_IN(PC_OUT),
        .BRANCH_ADDRESS(INSTRUCTION[15:8]),
        .BRANCH(BRANCH_CONTROL), 
        .JUMP(JUMP_CONTROL), 
        .ZERO(ZERO_FLAG),
        .PC_OUT(PC_IN)
    );
    
    control_unit u_control (
        .OPCODE (INSTRUCTION[7:0]),
        .WRITE_ENABLE(REG_WRITE_ENABLE),
        .ALUOP(ALUOP),
        .SIGN_CONTROL(SIGN_CONTROL),
        .OPERAND_CONTROL(OPERAND_CONTROL),
        .BRANCH_CONTROL(BRANCH_CONTROL),
        .JUMP_CONTROL(JUMP_CONTROL)
    );

    reg_file u_regfile (
        .INDATA(ALURESULT),
        .INADDRESS(INSTRUCTION[10:8]),
        .OUT1ADDRESS(INSTRUCTION[18:16]),
        .OUT2ADDRESS(INSTRUCTION[26:24]),
        .OUT1DATA(OPERAND1),
        .OUT2DATA(OPERAND2),
        .WRITE(REG_WRITE_ENABLE),
        .CLK(CLK),
        .RESET(RESET)
    ); 

    reg [7:0] ALU_IN_DATA1, ALU_IN_DATA2;

    always @(*) begin
        ALU_IN_DATA1 = OPERAND1;
        if (OPERAND_CONTROL) begin
            ALU_IN_DATA2 = INSTRUCTION[31:24];
        end
        else begin
            if (SIGN_CONTROL) begin
                ALU_IN_DATA2 <= #2 (~OPERAND2 + 8'b1);
            end
            else begin
                ALU_IN_DATA2 = OPERAND2;
            end
        end
    end    

    aluUnit u_alu (
        .DATA1(ALU_IN_DATA1),
        .DATA2(ALU_IN_DATA2),
        .ALUOP(ALUOP),
        .RESULT(ALURESULT),
        .ZERO(ZERO_FLAG)
    );
endmodule

cpu_tb.v
module cpu_tb;

    reg CLK, RESET;
    wire [31:0] PC;
    reg [31:0] INSTRUCTION;
    reg [7:0] instr_mem [0:1023];  // 1KB instruction memory
    integer i;

    // Instantiate the CPU
    CPU mycpu (
        .PC_OUT(PC),
        .INSTRUCTION(INSTRUCTION),
        .CLK(CLK),
        .RESET(RESET)
    );

    // Clock generation (period = 8 time units)
    always #4 CLK = ~CLK;

    // Instruction fetch on PC change
    always @(PC) begin
        // Instruction memory should be word-addressable in steps of 4
        INSTRUCTION <= #2 {
            instr_mem[PC + 0],
            instr_mem[PC + 1],
            instr_mem[PC + 2],
            instr_mem[PC + 3]
        };
        $display("->    Cycle %0d: PC = %0d, Instruction = %b", i, PC, INSTRUCTION);
    end

    initial begin
        // Load instruction memory from file
        $readmemb("instr_mem.mem", instr_mem);

        // Optional: Display initial memory (commented)
        /*
        $display("Instruction Memory Contents (First 32 Bytes):");
        for (i = 0; i < 32; i = i + 1) begin
            $display("addr[%0d] = %b", i, instr_mem[i]);
        end
        */

        // Initialize waveform dump
        $dumpfile("cpu_wavedata.vcd");
        $dumpvars(0, cpu_tb);
        /*
        $dumpvars(1, cpu_tb.mycpu.u_regfile.r0);
        $dumpvars(1, cpu_tb.mycpu.u_regfile.r1);
        $dumpvars(1, cpu_tb.mycpu.u_regfile.r2);
        $dumpvars(1, cpu_tb.mycpu.u_regfile.r3);
        $dumpvars(1, cpu_tb.mycpu.u_regfile.r4);
        $dumpvars(1, cpu_tb.mycpu.u_regfile.r5);
        $dumpvars(1, cpu_tb.mycpu.u_regfile.r6);
        $dumpvars(1, cpu_tb.mycpu.u_regfile.r7);
        */

        // Initialize signals
        CLK = 0;
        RESET = 1;
        #8; // Wait 8 time units for RESET to propagate
        @(posedge CLK);  // Sync with clock
        RESET = 0;

        // Run for 4 cycles
        for (i = 0; i < 5; i = i + 1) begin
            @(posedge CLK);
        end

        #10 $finish;
    end

endmodule

cpu_wavedata.vcd
$date
	Wed Jun 18 01:38:02 2025
$end
$version
	Icarus Verilog
$end
$timescale
	1s
$end
$scope module cpu_tb $end
$var wire 32 ! PC [31:0] $end
$var reg 1 " CLK $end
$var reg 32 # INSTRUCTION [31:0] $end
$var reg 1 $ RESET $end
$var integer 32 % i [31:0] $end
$scope module mycpu $end
$var wire 1 " CLK $end
$var wire 32 & INSTRUCTION [31:0] $end
$var wire 1 $ RESET $end
$var wire 1 ' ZERO_FLAG $end
$var wire 1 ( SIGN_CONTROL $end
$var wire 1 ) REG_WRITE_ENABLE $end
$var wire 32 * PC_OUT [31:0] $end
$var wire 32 + PC_IN [31:0] $end
$var wire 1 , OPERAND_CONTROL $end
$var wire 8 - OPERAND2 [7:0] $end
$var wire 8 . OPERAND1 [7:0] $end
$var wire 1 / JUMP_CONTROL $end
$var wire 2 0 BRANCH_CONTROL [1:0] $end
$var wire 8 1 ALURESULT [7:0] $end
$var wire 3 2 ALUOP [2:0] $end
$var reg 8 3 ALU_IN_DATA1 [7:0] $end
$var reg 8 4 ALU_IN_DATA2 [7:0] $end
$scope module u_alu $end
$var wire 8 5 DATA1 [7:0] $end
$var wire 8 6 DATA2 [7:0] $end
$var wire 8 7 sum [7:0] $end
$var wire 8 8 shiftOut [7:0] $end
$var wire 8 9 orOut [7:0] $end
$var wire 8 : mulOut [7:0] $end
$var wire 8 ; fwdOut [7:0] $end
$var wire 8 < andOut [7:0] $end
$var wire 3 = ALUOP [2:0] $end
$var reg 8 > RESULT [7:0] $end
$var reg 1 ' ZERO $end
$scope module u0 $end
$var wire 8 ? DATA2 [7:0] $end
$var wire 8 @ RESULT [7:0] $end
$upscope $end
$scope module u1 $end
$var wire 8 A DATA1 [7:0] $end
$var wire 8 B DATA2 [7:0] $end
$var wire 8 C RESULT [7:0] $end
$upscope $end
$scope module u3 $end
$var wire 8 D DATA1 [7:0] $end
$var wire 8 E DATA2 [7:0] $end
$var wire 8 F RESULT [7:0] $end
$upscope $end
$scope module u4 $end
$var wire 8 G DATA1 [7:0] $end
$var wire 8 H DATA2 [7:0] $end
$var wire 8 I RESULT [7:0] $end
$upscope $end
$scope module u5 $end
$var wire 8 J DATA1 [7:0] $end
$var wire 8 K DATA2 [7:0] $end
$var reg 16 L A [15:0] $end
$var reg 17 M P [16:0] $end
$var reg 8 N RESULT [7:0] $end
$var reg 16 O S [15:0] $end
$var integer 32 P i [31:0] $end
$upscope $end
$scope module u6 $end
$var wire 8 Q DATA1 [7:0] $end
$var wire 8 R DATA2 [7:0] $end
$var reg 8 S RESULT [7:0] $end
$var reg 1 T sign $end
$var integer 32 U i [31:0] $end
$upscope $end
$upscope $end
$scope module u_control $end
$var wire 8 V OPCODE [7:0] $end
$var reg 3 W ALUOP [2:0] $end
$var reg 2 X BRANCH_CONTROL [1:0] $end
$var reg 1 / JUMP_CONTROL $end
$var reg 1 , OPERAND_CONTROL $end
$var reg 1 ( SIGN_CONTROL $end
$var reg 1 ) WRITE_ENABLE $end
$upscope $end
$scope module u_pc $end
$var wire 1 " CLK $end
$var wire 1 $ RESET $end
$var wire 32 Y PC_IN [31:0] $end
$var reg 32 Z PC_OUT [31:0] $end
$upscope $end
$scope module u_pcIn $end
$var wire 2 [ BRANCH [1:0] $end
$var wire 8 \ BRANCH_ADDRESS [7:0] $end
$var wire 1 / JUMP $end
$var wire 32 ] PC_IN [31:0] $end
$var wire 1 ' ZERO $end
$var reg 32 ^ PC [31:0] $end
$var reg 32 _ PC_OUT [31:0] $end
$var reg 32 ` offset [31:0] $end
$upscope $end
$scope module u_regfile $end
$var wire 1 " CLK $end
$var wire 3 a INADDRESS [2:0] $end
$var wire 8 b INDATA [7:0] $end
$var wire 3 c OUT1ADDRESS [2:0] $end
$var wire 3 d OUT2ADDRESS [2:0] $end
$var wire 1 $ RESET $end
$var wire 1 ) WRITE $end
$var wire 8 e r0 [7:0] $end
$var wire 8 f r1 [7:0] $end
$var wire 8 g r2 [7:0] $end
$var wire 8 h r3 [7:0] $end
$var wire 8 i r4 [7:0] $end
$var wire 8 j r5 [7:0] $end
$var wire 8 k r6 [7:0] $end
$var wire 8 l r7 [7:0] $end
$var reg 8 m OUT1DATA [7:0] $end
$var reg 8 n OUT2DATA [7:0] $end
$var integer 32 o counter [31:0] $end
$upscope $end
$upscope $end
$upscope $end
$enddefinitions $end
#0
$dumpvars
bx o
bx n
bx m
bx l
bx k
bx j
bx i
bx h
bx g
bx f
bx e
bx d
bx c
bx b
bx a
bx `
bx _
bx ^
bx ]
bx \
bx [
bx Z
bx Y
bx X
bx W
bx V
bx U
xT
bx S
bx R
bx Q
bx P
bx O
bx N
bx M
bx L
bx K
bx J
bx I
bx H
bx G
bx F
bx E
bx D
bx C
bx B
bx A
bx @
bx ?
bx >
bx =
bx <
bx ;
bx :
bx 9
bx 8
bx 7
bx 6
bx 5
bx 4
bx 3
bx 2
bx 1
bx 0
x/
bx .
bx -
x,
bx +
bx *
x)
x(
x'
bx &
bx %
1$
bx #
0"
bx !
$end
#1
bx00 `
b0 !
b0 *
b0 Z
b0 ]
#2
bx00 +
bx00 Y
bx00 _
b100 ^
#3
b0 1
b0 >
b0 b
b1000 P
bx M
bx00000000 O
bx00000000 L
bx00000 8
bx00000 S
b101 U
b101 4
b101 6
b101 ?
b101 B
b101 E
b101 H
b101 K
b101 R
1)
1,
0(
0/
b0 0
b0 X
b0 [
b100 +
b100 Y
b100 _
b100 \
b0 V
b100 a
b0 c
b101 d
b10000 `
b101000000000000010000000000 #
b101000000000000010000000000 &
#4
b101 1
b101 >
b101 b
b0 2
b0 =
b0 W
b10000 `
b1000 o
b0x0x <
b0x0x F
bx1x1 9
bx1x1 I
b101 ;
b101 @
1"
#5
b0 l
b0 k
b0 j
b0 i
b0 h
b0 g
b0 f
b0 e
b10000 `
#6
b10000 `
#7
b1000 P
b0 M
b0 O
b0 L
b101 U
0T
b0 8
b0 S
b0 3
b0 5
b0 A
b0 D
b0 G
b0 J
b0 Q
b0 -
b0 n
b0 .
b0 m
b10000 `
#8
b10000 `
b0 <
b0 F
b101 9
b101 I
0"
#9
b10000 `
0'
b101 7
b101 C
#10
b10000 `
b0 :
b0 N
#11
b10000 `
#12
b10000 `
b0 %
0$
1"
#13
b100 !
b100 *
b100 Z
b100 ]
b101 i
b10000 `
#14
b1000 +
b1000 Y
b1000 _
b1000 ^
b10000 `
#15
b1000 P
b0 M
b1001 U
b1001 4
b1001 6
b1001 ?
b1001 B
b1001 E
b1001 H
b1001 K
b1001 R
b10 \
b10 a
b1 d
b1001000000000000001000000000 #
b1001000000000000001000000000 &
b1000 `
#16
b1000 `
b1001 1
b1001 >
b1001 b
b1001 9
b1001 I
b1001 ;
b1001 @
0"
#17
b1000 `
b1001 7
b1001 C
#18
b1000 `
#19
b1000 `
#20
b1000 `
b1 %
1"
#21
b1000 !
b1000 *
b1000 Z
b1000 ]
b1001 g
b1000 `
#22
b1100 +
b1100 Y
b1100 _
b1100 ^
b1000 `
#23
b1000 P
b0 M
b10 U
0,
b0 4
b0 6
b0 ?
b0 B
b0 E
b0 H
b0 K
b0 R
b110 \
b10 V
b110 a
b100 c
b10 d
b10000001000000011000000010 #
b10000001000000011000000010 &
b11000 `
#24
b1 2
b1 =
b1 W
b11000 `
b1001 1
b1001 >
b1001 b
b0 9
b0 I
b0 ;
b0 @
0"
#25
b1001 4
b1001 6
b1001 ?
b1001 B
b1001 E
b1001 H
b1001 K
b1001 R
b101 3
b101 5
b101 A
b101 D
b101 G
b101 J
b101 Q
b1001 -
b1001 n
b101 .
b101 m
b11000 `
1'
b0 1
b0 >
b0 b
b0 7
b0 C
#26
b11000 `
b1 <
b1 F
b1101 9
b1101 I
b1001 ;
b1001 @
#27
b11000 `
0'
b1110 1
b1110 >
b1110 b
b1110 7
b1110 C
#28
b11000 `
b10 %
1"
#29
b1100 !
b1100 *
b1100 Z
b1100 ]
b1110 k
b11000 `
#30
b10000 +
b10000 Y
b10000 _
b10000 ^
b11000 `
#31
b0 \
b1 V
b0 a
b0 c
b110 d
b110000000000000000000000001 #
b110000000000000000000000001 &
b0 `
#32
b1001 1
b1001 >
b1001 b
b0 2
b0 =
b0 W
b0 `
0"
#33
b1000 P
b0 M
b1110 U
b1110 4
b1110 6
b1110 ?
b1110 B
b1110 E
b1110 H
b1110 K
b1110 R
b0 3
b0 5
b0 A
b0 D
b0 G
b0 J
b0 Q
b1110 -
b1110 n
b0 .
b0 m
b0 `
#34
b0 `
b1110 1
b1110 >
b1110 b
b0 <
b0 F
b1110 9
b1110 I
b1110 ;
b1110 @
#35
b0 `
#36
b0 `
b11 %
1"
#37
b10000 !
b10000 *
b10000 Z
b10000 ]
b1110 e
b0 `
#38
b10100 +
b10100 Y
b10100 _
b10100 ^
b0 `
#39
b1 4
b1 6
b1 ?
b1 B
b1 E
b1 H
b1 K
b1 R
1,
b1000 P
b110001000 M
b1111001000000000 O
b111000000000 L
b1110 U
b0 8
b0 S
b1 \
b0 V
b1 a
b1 d
b1110 3
b1110 5
b1110 A
b1110 D
b1110 G
b1110 J
b1110 Q
b1000000000000000100000000 #
b1000000000000000100000000 &
b1110 .
b1110 m
b100 `
#40
b100 `
b1 1
b1 >
b1 b
b1111 9
b1111 I
b1 ;
b1 @
0"
#41
b0 -
b0 n
b100 `
b1111 7
b1111 C
#42
b100 `
b11000100 :
b11000100 N
#43
b100 `
#44
b100 `
b100 %
1"
#45
b10100 !
b10100 *
b10100 Z
b10100 ]
b1 f
b100 `
#46
b11000 +
b11000 Y
b11000 _
b11000 ^
b100 `
#47
0,
b10 \
b10 V
b10 a
b10 c
b1000000100000001000000010 #
b1000000100000001000000010 &
b1 -
b1 n
b1000 `
#48
b1111 1
b1111 >
b1111 b
b1 2
b1 =
b1 W
b1000 `
0"
#49
b1000 P
b10010 M
b1111011100000000 O
b100100000000 L
b1 U
b10010 8
b10010 S
b1001 3
b1001 5
b1001 A
b1001 D
b1001 G
b1001 J
b1001 Q
b1001 .
b1001 m
b1000 `
#50
b1000 `
b1 <
b1 F
b1001 9
b1001 I
#51
b1000 `
b1010 1
b1010 >
b1010 b
b1010 7
b1010 C
#52
b1000 `
b101 %
b1001 :
b1001 N
1"
#53
b11000 !
b11000 *
b11000 Z
b11000 ]
b1010 g
b1000 `
#54
b11100 +
b11100 Y
b11100 _
b11100 ^
b1000 `
#55
bx00 +
bx00 Y
bx00 _
x)
x,
x(
x/
bx 0
bx X
bx [
b1000 P
b10100 M
b1111011000000000 O
b101000000000 L
b1 U
b10100 8
b10100 S
bx \
bx V
bx a
bx c
bx d
b1010 3
b1010 5
b1010 A
b1010 D
b1010 G
b1010 J
b1010 Q
bx #
bx &
b1010 .
b1010 m
bx00 `
#56
b0 1
b0 >
b0 b
bx00 +
bx00 Y
bx00 _
bx 2
bx =
bx W
bx00 `
b0 <
b0 F
b1011 9
b1011 I
0"
#57
bx 4
bx 6
bx ?
bx B
bx E
bx H
bx K
bx R
bx 3
bx 5
bx A
bx D
bx G
bx J
bx Q
bx00 +
bx00 Y
bx00 _
bx -
bx n
bx .
bx m
bx00 `
b1011 7
b1011 C
#58
bx00 +
bx00 Y
bx00 _
bx00 `
bx <
bx F
bx 9
bx I
bx ;
bx @
b1010 :
b1010 N
#59
bx00 `
x'
bx 7
bx C
#60
bx00 +
bx00 Y
bx00 _
bx00 `
1"
#61
bx00 +
bx00 Y
bx00 _
bx00 !
bx00 *
bx00 Z
bx00 ]
bx00 `
#62
bx +
bx Y
bx _
bx ^
bx00 `
