FinalFunctioningUnits/Processor.v
// Author: S. Ganathipan [E/21/148], K. Jarshigan [E/21/188]
// Date: 2024-06-09
// Institution: Computer Engineering Department, Faculty of Engineering, UOP
// Description: Top-level processor and all submodules for CO224 Lab 5 Task 5. This file contains the Verilog implementation of the CPU datapath, ALU, control unit, register file, shifter, multiplier, and supporting modules. Each module is coded and commented for clarity and modularity. The design supports simulation and integration with instruction memory for full processor testing.

module fwdUnit (
    input [7:0] DATA2,
    output [7:0] RESULT);
    
    assign #1 RESULT = DATA2;
endmodule

module addUnit (
    input  [7:0] DATA1,
    input  [7:0] DATA2,
    output [7:0] RESULT);

    assign #2 RESULT = DATA1 + DATA2;
endmodule

module andUnit (
    input  [7:0] DATA1,
    input  [7:0] DATA2,
    output [7:0] RESULT);

    assign #1 RESULT = DATA1 & DATA2;
endmodule

module orUnit (
    input  [7:0] DATA1,
    input  [7:0] DATA2,
    output [7:0] RESULT);

    assign #1 RESULT = DATA1 | DATA2;
endmodule

module mulUnit (
    input  signed [7:0] DATA1,      // Multiplicand
    input  signed [7:0] DATA2,      // Multiplier
    input ENABLE,
    output reg signed [7:0] RESULT // Final 16-bit signed product
    );

    integer i;
    reg [15:0] temp1, temp2;

    always @(*) begin
        temp1 = 16'b0;
        temp2 = {8'b0, DATA1};

        for (i = 0; i < 8; i = i + 1) begin
            if (DATA2[i]) temp1 = temp1 + temp2;
            temp2 = {temp2, 1'b0};
        end

        RESULT = ENABLE ? temp1[7:0] : 8'b0; 
    end
endmodule

module shifterUnit (    
    input  [7:0] DATA1,     // 8-bit input DATA1
    input  [7:0] DATA2,     // 8-bit input DATA2
    input  ENABLE,
    output reg [7:0] RESULT // 8-bit output RESULT
    );

    integer i;
    reg sign;

    always @(*) begin
        if (ENABLE) begin
        RESULT = DATA1;
        sign = DATA1[7];
        for (i = 0; i < DATA2[3:0]; i = i + 1) begin
            case (DATA2[5:4])
                2'b00: RESULT = {RESULT[6:0], 1'b0};          // Logical shift left (sll)
                2'b01: RESULT = {1'b0, RESULT[7:1]};          // Logical shift right (srl)
                2'b10: RESULT = {sign, RESULT[7:1]};          // Arithmetic shift right (sra)
                2'b11: RESULT = {RESULT[0], RESULT[7:1]};     // Rotate right (ror)
            endcase
        end
        //#4; // Delay for shifting
        end 
        else begin
            RESULT = 8'B0;
        end
    end
endmodule

module aluUnit(
    input [7:0] DATA1,        // 8-bit input DATA1
    input [7:0] DATA2,        // 8-bit input DATA2
    input [2:0] ALUOP,     // 3-bit selector to choose operation
    output reg [7:0] RESULT,   // 8-bit output RESULT
    output reg ZERO
    );

    wire [7:0] sum, andOut, orOut, fwdOut, mulOut, shiftOut;
    wire SHIFT_E;

    assign SHIFT_E = (ALUOP == 3'b101) ? 1'b1: 1'b0;
    assign MUL_E   = (ALUOP == 3'b100) ? 1'b1: 1'b0;

    fwdUnit     u0 (.RESULT(fwdOut)  , .DATA2(DATA2));
    addUnit     u1 (.RESULT(sum)     , .DATA1(DATA1), .DATA2(DATA2));
    andUnit     u3 (.RESULT(andOut)  , .DATA1(DATA1), .DATA2(DATA2));
    orUnit      u4 (.RESULT(orOut)   , .DATA1(DATA1), .DATA2(DATA2));
    mulUnit     u5 (.RESULT(mulOut)  , .DATA1(DATA1), .DATA2(DATA2), .ENABLE(MUL_E));
    shifterUnit u6 (.RESULT(shiftOut), .DATA1(DATA1), .DATA2(DATA2), .ENABLE(SHIFT_E));
    
    always @(*) begin
        case (ALUOP)
            3'b000: RESULT = fwdOut;    
            3'b001: RESULT = sum;      
            3'b010: RESULT = andOut;  
            3'b011: RESULT = orOut;
            3'b100: RESULT = mulOut;
            3'b101: RESULT = shiftOut;                
            default: RESULT = 8'b0; 
        endcase

        // Sets the ZERO flag if the result is zero
        ZERO = (sum == 0) ? 1'b1: 1'b0;  
    end
endmodule

module reg_file(
    input [7:0] INDATA,             
    input [2:0] INADDRESS,          
    input [2:0] OUT1ADDRESS,        
    input [2:0] OUT2ADDRESS,        
    output reg [7:0] OUT1DATA,      
    output reg [7:0] OUT2DATA,      
    input CLK,                      
    input RESET,                    
    input  WRITE                    
    );

    reg [7:0] reg_array [0:7]; 

    always @(*) begin
        OUT1DATA <= #2 reg_array[OUT1ADDRESS];  
        OUT2DATA <= #2 reg_array[OUT2ADDRESS];  
    end

    always @(posedge CLK) begin
        if(WRITE == 1'b1  &&  RESET == 1'b0) begin 
            reg_array[INADDRESS] <= #1 INDATA;
        end
    end

    integer counter;             
    always @(posedge CLK) begin
        if(RESET == 1'b1) begin
            for(counter = 0; counter < 8; counter = counter + 1) begin
                reg_array[counter] <= #1 8'b00000000;
            end
        end
    end
endmodule

module control_unit(
    input [7:0] OPCODE,
    output reg WRITE_ENABLE,
    output reg [2:0] ALUOP,
    output reg SIGN_CONTROL,
    output reg OPERAND_CONTROL,
    output reg [1:0] BRANCH_CONTROL,
    output reg JUMP_CONTROL
    );

    // ALU operation codes
    localparam OP_LOADI = 8'b00000000;
    localparam OP_MOV   = 8'b00000001;
    localparam OP_ADD   = 8'b00000010;
    localparam OP_SUB   = 8'b00000011;
    localparam OP_AND   = 8'b00000100;
    localparam OP_OR    = 8'b00000101;
    localparam OP_J     = 8'b00000110;
    localparam OP_BEQ   = 8'b00000111;
    
    localparam OP_MUL   = 8'b00001000;
    localparam OP_SHIFT = 8'b00001001;
    localparam OP_BNE   = 8'b00001010;

    always @(OPCODE) begin 
        ALUOP <= #1 (OPCODE == OP_ADD)   ? 3'b001 :
                (OPCODE == OP_SUB)   ? 3'b001 :
                (OPCODE == OP_AND)   ? 3'b010 :
                (OPCODE == OP_OR)    ? 3'b011 :
                (OPCODE == OP_MOV)   ? 3'b000 :
                (OPCODE == OP_LOADI) ? 3'b000 :
                (OPCODE == OP_MUL)   ? 3'b100 :
                (OPCODE == OP_SHIFT) ? 3'b101 :
                3'b000;

        BRANCH_CONTROL   = (OPCODE == OP_BEQ)   ? 2'b01 : 
                           (OPCODE == OP_BNE)   ? 2'b10 : 2'b00;

        JUMP_CONTROL     = (OPCODE == OP_J)     ? 1'b1 : 1'b0;

        SIGN_CONTROL     = (OPCODE == OP_SUB || OPCODE == OP_BEQ || OPCODE == OP_BNE)   ? 1'b1 : 1'b0;

        OPERAND_CONTROL  = (OPCODE == OP_LOADI || OPCODE == OP_SHIFT) ? 1'b1 : 1'b0;

        WRITE_ENABLE  = (OPCODE == OP_LOADI || OPCODE == OP_MOV || OPCODE == OP_ADD ||
                    OPCODE == OP_SUB || OPCODE == OP_AND || OPCODE == OP_OR ||
                    OPCODE == OP_MUL || OPCODE == OP_SHIFT) ? 1'b1 : 1'b0;
    end
endmodule

module ProgramCounter(
    input CLK, RESET,
    input      [31:0] PC_IN,
    output reg [31:0] PC_OUT
    );

    always @(posedge CLK or posedge RESET) begin 
        if (RESET) begin
            PC_OUT <= #1 32'b0;
        end
        else begin
            PC_OUT <= #1 PC_IN;
        end
    end
endmodule

module pcIncrementer (
    input [31:0] PC_IN,
    input [7:0]  BRANCH_ADDRESS,
    input [1:0]  BRANCH, 
    input        JUMP, ZERO,
    output reg [31:0] PC_OUT
    );

    reg [31:0] PC;
    reg [31:0] offset;

    always @(*) begin
        PC <= #1 PC_IN + 32'd4;
 
        offset <= #2 PC + {{22{BRANCH_ADDRESS[7]}}, BRANCH_ADDRESS, 2'b00}; 

        PC_OUT =    JUMP ? offset : 
                    (BRANCH == 2'b01 && ZERO) ? offset : 
                    (BRANCH == 2'b10 && !ZERO) ? offset : PC;
    end
endmodule

module CPU(
    input [31:0] INSTRUCTION,
    input CLK, RESET, 
    output wire [31:0] PC_OUT
    );

    wire [7:0] OPERAND1, OPERAND2, ALURESULT;
    wire [2:0] ALUOP;
    wire REG_WRITE_ENABLE;
    wire SIGN_CONTROL, OPERAND_CONTROL;

    wire [1:0] BRANCH_CONTROL;
    wire JUMP_CONTROL;
    wire ZERO_FLAG;        
    wire [31:0] PC_IN;

    ProgramCounter u_pc (
        .CLK(CLK),
        .RESET(RESET),
        .PC_IN(PC_IN),
        .PC_OUT(PC_OUT)
    );

    pcIncrementer u_pcIn (
        .PC_IN(PC_OUT),
        .BRANCH_ADDRESS(INSTRUCTION[15:8]),
        .BRANCH(BRANCH_CONTROL), 
        .JUMP(JUMP_CONTROL), 
        .ZERO(ZERO_FLAG),
        .PC_OUT(PC_IN)
    );
    
    control_unit u_control (
        .OPCODE (INSTRUCTION[7:0]),
        .WRITE_ENABLE(REG_WRITE_ENABLE),
        .ALUOP(ALUOP),
        .SIGN_CONTROL(SIGN_CONTROL),
        .OPERAND_CONTROL(OPERAND_CONTROL),
        .BRANCH_CONTROL(BRANCH_CONTROL),
        .JUMP_CONTROL(JUMP_CONTROL)
    );

    reg_file u_regfile (
        .INDATA(ALURESULT),
        .INADDRESS(INSTRUCTION[10:8]),
        .OUT1ADDRESS(INSTRUCTION[18:16]),
        .OUT2ADDRESS(INSTRUCTION[26:24]),
        .OUT1DATA(OPERAND1),
        .OUT2DATA(OPERAND2),
        .WRITE(REG_WRITE_ENABLE),
        .CLK(CLK),
        .RESET(RESET)
    ); 

    reg [7:0] ALU_IN_DATA1, ALU_IN_DATA2;

    always @(*) begin
        ALU_IN_DATA1 = OPERAND1;
        if (OPERAND_CONTROL) begin
            ALU_IN_DATA2 = INSTRUCTION[31:24];
        end
        else begin
            if (SIGN_CONTROL) begin
                ALU_IN_DATA2 <= #2 (~OPERAND2 + 8'b1);
            end
            else begin
                ALU_IN_DATA2 = OPERAND2;
            end
        end
    end    

    aluUnit u_alu (
        .DATA1(ALU_IN_DATA1),
        .DATA2(ALU_IN_DATA2),
        .ALUOP(ALUOP),
        .RESULT(ALURESULT),
        .ZERO(ZERO_FLAG)
    );
endmodule

FinalFunctioningUnits/cpu_tb.v
// Author: S. Ganathipan [E/21/148], K. Jarshigan [E/21/188]
// Date: 2024-06-09
// Institution: Computer Engineering Department, Faculty of Engineering, UOP
// Description: Testbench for the CO224 Lab 5 Task 5 processor. This file simulates the CPU, loads instructions from memory, generates the clock and reset signals, and dumps waveforms for analysis. It is used to verify the correct operation of the processor and observe register/memory behavior during execution.

module cpu_tb;

    reg CLK, RESET;
    wire [31:0] PC;
    reg [31:0] INSTRUCTION;
    reg [7:0] instr_mem [0:1023];  // 1KB instruction memory
    integer i;

    // Instantiate the CPU
    CPU mycpu (
        .PC_OUT(PC),
        .INSTRUCTION(INSTRUCTION),
        .CLK(CLK),
        .RESET(RESET)
    );

    // Clock generation (period = 10 time units)
    always #6 CLK = ~CLK;

    // Instruction fetch on PC change
    always @(PC) begin
        // Instruction memory should be word-addressable in steps of 4
        INSTRUCTION <= #2 {
            instr_mem[PC + 0],
            instr_mem[PC + 1],
            instr_mem[PC + 2],
            instr_mem[PC + 3]
        };
    end        

    initial begin
        // Load instruction memory from file
        $readmemb("InstructionMemory/instr_mem.mem", instr_mem);

        // Initialize waveform dump
        $dumpfile("FinalFunctioningUnits/cpu_wavedata.vcd");
        $dumpvars(0, cpu_tb);
        $dumpvars(1, cpu_tb.mycpu.u_regfile.reg_array[0]);
        $dumpvars(1, cpu_tb.mycpu.u_regfile.reg_array[1]);
        $dumpvars(1, cpu_tb.mycpu.u_regfile.reg_array[2]);
        $dumpvars(1, cpu_tb.mycpu.u_regfile.reg_array[3]);
        $dumpvars(1, cpu_tb.mycpu.u_regfile.reg_array[4]);
        $dumpvars(1, cpu_tb.mycpu.u_regfile.reg_array[5]);
        $dumpvars(1, cpu_tb.mycpu.u_regfile.reg_array[6]);
        $dumpvars(1, cpu_tb.mycpu.u_regfile.reg_array[7]);

        // Initialize signals
        CLK = 0;
        RESET = 1;
        #8; // Wait 8 time units for RESET to propagate
        @(posedge CLK);  // Sync with clock
        RESET = 0;
        $display("->    Cycle %0d: PC = %0d, Instruction = %b %b %b %b", i, PC, INSTRUCTION[31:24], INSTRUCTION[23:16], INSTRUCTION[15:8], INSTRUCTION[7:0]);

        // Run for 20 cycles and display PC and instruction at each cycle
        for (i = 0; i < 30; i = i + 1) begin
            @(posedge CLK);
            $display("->    Cycle %0d: PC = %0d, Instruction = %b %b %b %b", i, PC, INSTRUCTION[31:24], INSTRUCTION[23:16], INSTRUCTION[15:8], INSTRUCTION[7:0]);
        end

        #10 $finish;
    end
endmodule

FinalFunctioningUnits/cpu_wavedata.vcd
$date
	Sun Jun 22 01:33:26 2025
$end
$version
	Icarus Verilog
$end
$timescale
	1s
$end
$scope module cpu_tb $end
$var wire 32 ! PC [31:0] $end
$var reg 1 " CLK $end
$var reg 32 # INSTRUCTION [31:0] $end
$var reg 1 $ RESET $end
$var integer 32 % i [31:0] $end
$scope module mycpu $end
$var wire 1 " CLK $end
$var wire 32 & INSTRUCTION [31:0] $end
$var wire 1 $ RESET $end
$var wire 1 ' ZERO_FLAG $end
$var wire 1 ( SIGN_CONTROL $end
$var wire 1 ) REG_WRITE_ENABLE $end
$var wire 32 * PC_OUT [31:0] $end
$var wire 32 + PC_IN [31:0] $end
$var wire 1 , OPERAND_CONTROL $end
$var wire 8 - OPERAND2 [7:0] $end
$var wire 8 . OPERAND1 [7:0] $end
$var wire 1 / JUMP_CONTROL $end
$var wire 2 0 BRANCH_CONTROL [1:0] $end
$var wire 8 1 ALURESULT [7:0] $end
$var wire 3 2 ALUOP [2:0] $end
$var reg 8 3 ALU_IN_DATA1 [7:0] $end
$var reg 8 4 ALU_IN_DATA2 [7:0] $end
$scope module u_alu $end
$var wire 8 5 DATA1 [7:0] $end
$var wire 8 6 DATA2 [7:0] $end
$var wire 8 7 sum [7:0] $end
$var wire 8 8 shiftOut [7:0] $end
$var wire 8 9 orOut [7:0] $end
$var wire 8 : mulOut [7:0] $end
$var wire 8 ; fwdOut [7:0] $end
$var wire 8 < andOut [7:0] $end
$var wire 1 = SHIFT_E $end
$var wire 1 > MUL_E $end
$var wire 3 ? ALUOP [2:0] $end
$var reg 8 @ RESULT [7:0] $end
$var reg 1 ' ZERO $end
$scope module u0 $end
$var wire 8 A DATA2 [7:0] $end
$var wire 8 B RESULT [7:0] $end
$upscope $end
$scope module u1 $end
$var wire 8 C DATA1 [7:0] $end
$var wire 8 D DATA2 [7:0] $end
$var wire 8 E RESULT [7:0] $end
$upscope $end
$scope module u3 $end
$var wire 8 F DATA1 [7:0] $end
$var wire 8 G DATA2 [7:0] $end
$var wire 8 H RESULT [7:0] $end
$upscope $end
$scope module u4 $end
$var wire 8 I DATA1 [7:0] $end
$var wire 8 J DATA2 [7:0] $end
$var wire 8 K RESULT [7:0] $end
$upscope $end
$scope module u5 $end
$var wire 8 L DATA1 [7:0] $end
$var wire 8 M DATA2 [7:0] $end
$var wire 1 > ENABLE $end
$var reg 8 N RESULT [7:0] $end
$var reg 16 O temp1 [15:0] $end
$var reg 16 P temp2 [15:0] $end
$var integer 32 Q i [31:0] $end
$upscope $end
$scope module u6 $end
$var wire 8 R DATA1 [7:0] $end
$var wire 8 S DATA2 [7:0] $end
$var wire 1 = ENABLE $end
$var reg 8 T RESULT [7:0] $end
$var reg 1 U sign $end
$var integer 32 V i [31:0] $end
$upscope $end
$upscope $end
$scope module u_control $end
$var wire 8 W OPCODE [7:0] $end
$var reg 3 X ALUOP [2:0] $end
$var reg 2 Y BRANCH_CONTROL [1:0] $end
$var reg 1 / JUMP_CONTROL $end
$var reg 1 , OPERAND_CONTROL $end
$var reg 1 ( SIGN_CONTROL $end
$var reg 1 ) WRITE_ENABLE $end
$upscope $end
$scope module u_pc $end
$var wire 1 " CLK $end
$var wire 1 $ RESET $end
$var wire 32 Z PC_IN [31:0] $end
$var reg 32 [ PC_OUT [31:0] $end
$upscope $end
$scope module u_pcIn $end
$var wire 2 \ BRANCH [1:0] $end
$var wire 8 ] BRANCH_ADDRESS [7:0] $end
$var wire 1 / JUMP $end
$var wire 32 ^ PC_IN [31:0] $end
$var wire 1 ' ZERO $end
$var reg 32 _ PC [31:0] $end
$var reg 32 ` PC_OUT [31:0] $end
$var reg 32 a offset [31:0] $end
$upscope $end
$scope module u_regfile $end
$var wire 1 " CLK $end
$var wire 3 b INADDRESS [2:0] $end
$var wire 8 c INDATA [7:0] $end
$var wire 3 d OUT1ADDRESS [2:0] $end
$var wire 3 e OUT2ADDRESS [2:0] $end
$var wire 1 $ RESET $end
$var wire 1 ) WRITE $end
$var reg 8 f OUT1DATA [7:0] $end
$var reg 8 g OUT2DATA [7:0] $end
$var integer 32 h counter [31:0] $end
$upscope $end
$upscope $end
$upscope $end
$scope module cpu_tb $end
$scope module mycpu $end
$scope module u_regfile $end
$var reg 8 i \reg_array[0] [7:0] $end
$upscope $end
$upscope $end
$upscope $end
$scope module cpu_tb $end
$scope module mycpu $end
$scope module u_regfile $end
$var reg 8 j \reg_array[1] [7:0] $end
$upscope $end
$upscope $end
$upscope $end
$scope module cpu_tb $end
$scope module mycpu $end
$scope module u_regfile $end
$var reg 8 k \reg_array[2] [7:0] $end
$upscope $end
$upscope $end
$upscope $end
$scope module cpu_tb $end
$scope module mycpu $end
$scope module u_regfile $end
$var reg 8 l \reg_array[3] [7:0] $end
$upscope $end
$upscope $end
$upscope $end
$scope module cpu_tb $end
$scope module mycpu $end
$scope module u_regfile $end
$var reg 8 m \reg_array[4] [7:0] $end
$upscope $end
$upscope $end
$upscope $end
$scope module cpu_tb $end
$scope module mycpu $end
$scope module u_regfile $end
$var reg 8 n \reg_array[5] [7:0] $end
$upscope $end
$upscope $end
$upscope $end
$scope module cpu_tb $end
$scope module mycpu $end
$scope module u_regfile $end
$var reg 8 o \reg_array[6] [7:0] $end
$upscope $end
$upscope $end
$upscope $end
$scope module cpu_tb $end
$scope module mycpu $end
$scope module u_regfile $end
$var reg 8 p \reg_array[7] [7:0] $end
$upscope $end
$upscope $end
$upscope $end
$enddefinitions $end
#0
$dumpvars
bx p
bx o
bx n
bx m
bx l
bx k
bx j
bx i
bx h
bx g
bx f
bx e
bx d
b0 c
bx b
bx a
bx `
bx _
bx ^
bx ]
bx \
bx [
bx Z
bx Y
bx X
bx W
bx V
xU
b0 T
bx S
bx R
b1000 Q
bx00000000 P
b0 O
b0 N
bx M
bx L
bx K
bx J
bx I
bx H
bx G
bx F
bx E
bx D
bx C
bx B
bx A
b0 @
bx ?
x>
x=
bx <
bx ;
b0 :
bx 9
b0 8
bx 7
bx 6
bx 5
bx 4
bx 3
bx 2
b0 1
bx 0
x/
bx .
bx -
x,
bx +
bx *
x)
x(
x'
bx &
bx %
1$
bx #
0"
bx !
$end
#1
b0 !
b0 *
b0 [
b0 ^
#2
b100 _
#3
b1000 Q
bx00000000 P
b0 4
b0 6
b0 A
b0 D
b0 G
b0 J
b0 M
b0 S
b100 +
b100 Z
b100 `
1)
1,
0(
0/
b0 0
b0 Y
b0 \
b0 ]
b0 W
b0 b
b0 d
b0 e
b0 #
b0 &
#4
b1000 Q
bx00000000 P
0>
0=
b0 2
b0 ?
b0 X
b0 <
b0 H
b0 ;
b0 B
#5
b100 a
#6
b1000 h
1"
#7
b0 p
b0 o
b0 n
b0 m
b0 l
b0 k
b0 j
b0 i
#9
b1000 Q
b0 P
b0 3
b0 5
b0 C
b0 F
b0 I
b0 L
b0 R
b0 -
b0 g
b0 .
b0 f
#10
b0 9
b0 K
#11
1'
b0 7
b0 E
#12
0"
#18
b0 %
0$
1"
#19
b100 !
b100 *
b100 [
b100 ^
b0 i
#20
b1000 +
b1000 Z
b1000 `
b1000 _
#21
b1000 Q
b11 4
b11 6
b11 A
b11 D
b11 G
b11 J
b11 M
b11 S
b1 ]
b1 b
b11 e
b11000000000000000100000000 #
b11000000000000000100000000 &
#22
b1000 a
b11 1
b11 @
b11 c
b11 9
b11 K
b11 ;
b11 B
#23
b1100 a
0'
b11 7
b11 E
#24
0"
#30
b1 %
1"
#31
b1000 !
b1000 *
b1000 [
b1000 ^
b11 j
#32
b1100 +
b1100 Z
b1100 `
b1100 _
#33
b1000 Q
b1 4
b1 6
b1 A
b1 D
b1 G
b1 J
b1 M
b1 S
b10 ]
b10 b
b1 e
b1000000000000001000000000 #
b1000000000000001000000000 &
#34
b10000 a
b1 1
b1 @
b1 c
b1 9
b1 K
b1 ;
b1 B
#35
b10100 a
b11 -
b11 g
b1 7
b1 E
#36
0"
#42
b10 %
1"
#43
b1100 !
b1100 *
b1100 [
b1100 ^
b1 k
#44
b10000 +
b10000 Z
b10000 `
b10000 _
#45
b1000 Q
b0 4
b0 6
b0 A
b0 D
b0 G
b0 J
b0 M
b0 S
b11 ]
b11 b
b0 e
b1100000000 #
b1100000000 &
#46
b11000 a
b0 1
b0 @
b0 c
b0 9
b0 K
b0 ;
b0 B
#47
b11100 a
b0 -
b0 g
1'
b0 7
b0 E
#48
0"
#54
b11 %
1"
#55
b10000 !
b10000 *
b10000 [
b10000 ^
b0 l
#56
b10100 +
b10100 Z
b10100 `
b10100 _
#57
b1000 Q
b1111 4
b1111 6
b1111 A
b1111 D
b1111 G
b1111 J
b1111 M
b1111 S
b110 ]
b110 b
b111 e
b1111000000000000011000000000 #
b1111000000000000011000000000 &
#58
b100000 a
b1111 1
b1111 @
b1111 c
b1111 9
b1111 K
b1111 ;
b1111 B
#59
b101100 a
0'
b1111 7
b1111 E
#60
0"
#66
b100 %
1"
#67
b10100 !
b10100 *
b10100 [
b10100 ^
b1111 o
#68
b11000 +
b11000 Z
b11000 `
b11000 _
#69
b1000 Q
0,
b0 4
b0 6
b0 A
b0 D
b0 G
b0 J
b0 M
b0 S
b11 ]
b10 W
b11 b
b11 d
b10 e
b10000000110000001100000010 #
b10000000110000001100000010 &
#70
b1 2
b1 ?
b1 X
b110000 a
b1111 1
b1111 @
b1111 c
b0 9
b0 K
b0 ;
b0 B
#71
b1000 Q
b1 4
b1 6
b1 A
b1 D
b1 G
b1 J
b1 M
b1 S
b100100 a
b1 -
b1 g
1'
b0 1
b0 @
b0 c
b0 7
b0 E
#72
b1 9
b1 K
b1 ;
b1 B
0"
#73
0'
b1 1
b1 @
b1 c
b1 7
b1 E
#78
b101 %
1"
#79
b11000 !
b11000 *
b11000 [
b11000 ^
b1 l
#80
b11100 +
b11100 Z
b11100 `
b11100 _
#81
1,
b1 O
b1000 Q
b100000000 P
b100 ]
b1001 W
b100 b
b110 d
b1 e
b1 3
b1 5
b1 C
b1 F
b1 I
b1 L
b1 R
b1000001100000010000001001 #
b1000001100000010000001001 &
b1 .
b1 f
#82
b1 V
0U
b10 8
b10 T
1=
b10 1
b10 @
b10 c
b101 2
b101 ?
b101 X
b101000 a
b1 <
b1 H
#83
b11110 1
b11110 @
b11110 c
b1000 Q
b111100000000 P
b1111 O
b1 V
b11110 8
b11110 T
b1111 3
b1111 5
b1111 C
b1111 F
b1111 I
b1111 L
b1111 R
b101100 a
b11 -
b11 g
b1111 .
b1111 f
b10 7
b10 E
#84
b1111 9
b1111 K
0"
#85
b10000 7
b10000 E
#90
b110 %
1"
#91
b11100 !
b11100 *
b11100 [
b11100 ^
b11110 m
#92
b100000 +
b100000 Z
b100000 `
b100000 _
#93
b111 1
b111 @
b111 c
b1000 Q
b111100000000 P
b11111111 O
b1 V
b111 8
b111 T
b10001 4
b10001 6
b10001 A
b10001 D
b10001 G
b10001 J
b10001 M
b10001 S
b101 ]
b101 b
b10001000001100000010100001001 #
b10001000001100000010100001001 &
#94
b110000 a
b11111 9
b11111 K
b10001 ;
b10001 B
#95
b110100 a
b100000 7
b100000 E
#96
0"
#102
b111 %
1"
#103
b100000 !
b100000 *
b100000 [
b100000 ^
b111 n
#104
b100100 +
b100100 Z
b100100 `
b100100 _
#105
b1000 Q
b111100000000 P
b111101111 O
b1 V
b111 8
b111 T
b100001 4
b100001 6
b100001 A
b100001 D
b100001 G
b100001 J
b100001 M
b100001 S
b111 ]
b111 b
b100001000001100000011100001001 #
b100001000001100000011100001001 &
#106
b111000 a
b101111 9
b101111 K
b100001 ;
b100001 B
#107
b1000000 a
b110000 7
b110000 E
#108
0"
#114
b1000 %
1"
#115
b100100 !
b100100 *
b100100 [
b100100 ^
b111 p
#116
b101000 +
b101000 Z
b101000 `
b101000 _
#117
b10000111 1
b10000111 @
b10000111 c
b1000 Q
b111100000000 P
b1011011111 O
b1 V
b10000111 8
b10000111 T
b110001 4
b110001 6
b110001 A
b110001 D
b110001 G
b110001 J
b110001 M
b110001 S
b110 ]
b110 b
b110001000001100000011000001001 #
b110001000001100000011000001001 &
#118
b1000100 a
b111111 9
b111111 K
b110001 ;
b110001 B
#119
b1000000 a
b1000000 7
b1000000 E
#120
0"
#126
b1001 %
1"
#127
b101000 !
b101000 *
b101000 [
b101000 ^
b10000111 o
#128
b101100 +
b101100 Z
b101100 `
b101100 _
#129
b11100 1
b11100 @
b11100 c
0,
1(
b1000 Q
b1000011100000000 P
b100001110 O
b11100 8
b11100 T
b10 V
1U
b1 ]
b11 W
b1 b
b1 d
b10 e
b10 4
b10 6
b10 A
b10 D
b10 G
b10 J
b10 M
b10 S
b10000111 3
b10000111 5
b10000111 C
b10000111 F
b10000111 I
b10000111 L
b10000111 R
b10000000010000000100000011 #
b10000000010000000100000011 &
b10000111 .
b10000111 f
#130
b0 8
b0 T
0=
b1000000 1
b1000000 @
b1000000 c
b1 2
b1 ?
b1 X
b1000100 a
b10 <
b10 H
b10000111 9
b10000111 K
b10 ;
b10 B
#131
b1000 Q
b1100000000 P
b1011110111 O
b11 3
b11 5
b11 C
b11 F
b11 I
b11 L
b11 R
b11111101 4
b11111101 6
b11111101 A
b11111101 D
b11111101 G
b11111101 J
b11111101 M
b11111101 S
b110000 a
b1 -
b1 g
b11 .
b11 f
b10001001 1
b10001001 @
b10001001 c
b10001001 7
b10001001 E
#132
b1 <
b1 H
b11111111 9
b11111111 K
b11111101 ;
b11111101 B
0"
#133
b1000 Q
b1100000000 P
b1011111101 O
b11111111 4
b11111111 6
b11111111 A
b11111111 D
b11111111 G
b11111111 J
b11111111 M
b11111111 S
1'
b0 1
b0 @
b0 c
b0 7
b0 E
#134
b11 <
b11 H
b11111111 ;
b11111111 B
#135
0'
b10 1
b10 @
b10 c
b10 7
b10 E
#138
b1010 %
1"
#139
b101100 !
b101100 *
b101100 [
b101100 ^
b10 j
#140
b110000 +
b110000 Z
b110000 `
b110000 _
#141
0)
b10 0
b10 Y
b10 \
b1000 Q
b1000000000 P
b111111110 O
b11111001 ]
b1010 W
b0 e
b10 3
b10 5
b10 C
b10 F
b10 I
b10 L
b10 R
b11111100100001010 #
b11111100100001010 &
b10 .
b10 f
#142
b11111111 1
b11111111 @
b11111111 c
b110100 +
b110100 Z
b110100 `
b0 2
b0 ?
b0 X
b110100 a
b10 <
b10 H
#143
b10100 +
b10100 Z
b10100 `
b10100 a
b0 -
b0 g
b1 7
b1 E
#144
0"
#145
b1000 Q
b1000000000 P
b0 O
b0 4
b0 6
b0 A
b0 D
b0 G
b0 J
b0 M
b0 S
#146
b0 1
b0 @
b0 c
b0 <
b0 H
b10 9
b10 K
b0 ;
b0 B
#147
b10 7
b10 E
#150
b1011 %
1"
#151
b10100 !
b10100 *
b10100 [
b10100 ^
#152
b11000 _
#153
b11000 +
b11000 Z
b11000 `
1)
0(
b0 0
b0 Y
b0 \
b11 ]
b10 W
b11 b
b11 d
b10 e
b10000000110000001100000010 #
b10000000110000001100000010 &
#154
b10 1
b10 @
b10 c
b1 2
b1 ?
b1 X
b11111111111111111111111111111100 a
#155
b1 O
b1000 Q
b100000000 P
b1 4
b1 6
b1 A
b1 D
b1 G
b1 J
b1 M
b1 S
b1 3
b1 5
b1 C
b1 F
b1 I
b1 L
b1 R
b100100 a
b1 -
b1 g
b1 .
b1 f
#156
b1 <
b1 H
b1 9
b1 K
b1 ;
b1 B
0"
#162
b1100 %
1"
#163
b11000 !
b11000 *
b11000 [
b11000 ^
b10 l
#164
b11100 +
b11100 Z
b11100 `
b11100 _
#165
1,
b1000 Q
b1000000000 P
b10 O
b100 ]
b1001 W
b100 b
b110 d
b1 e
b10 3
b10 5
b10 C
b10 F
b10 I
b10 L
b10 R
b1000001100000010000001001 #
b1000001100000010000001001 &
b10 .
b10 f
#166
b1 V
0U
b100 8
b100 T
1=
b100 1
b100 @
b100 c
b101 2
b101 ?
b101 X
b101000 a
b0 <
b0 H
b11 9
b11 K
#167
b1110 1
b1110 @
b1110 c
b1000 Q
b1000011100000000 P
b10000111 O
b1 V
1U
b1110 8
b1110 T
b10000111 3
b10000111 5
b10000111 C
b10000111 F
b10000111 I
b10000111 L
b10000111 R
b101100 a
b10 -
b10 g
b10000111 .
b10000111 f
b11 7
b11 E
#168
b1 <
b1 H
b10000111 9
b10000111 K
0"
#169
b10001000 7
b10001000 E
#174
b1101 %
1"
#175
b11100 !
b11100 *
b11100 [
b11100 ^
b1110 m
#176
b100000 +
b100000 Z
b100000 `
b100000 _
#177
b1000011 1
b1000011 @
b1000011 c
b1000 Q
b1000011100000000 P
b100011110111 O
b1 V
b1000011 8
b1000011 T
b10001 4
b10001 6
b10001 A
b10001 D
b10001 G
b10001 J
b10001 M
b10001 S
b101 ]
b101 b
b10001000001100000010100001001 #
b10001000001100000010100001001 &
#178
b110000 a
b10010111 9
b10010111 K
b10001 ;
b10001 B
#179
b110100 a
b10011000 7
b10011000 E
#180
0"
#186
b1110 %
1"
#187
b100000 !
b100000 *
b100000 [
b100000 ^
b1000011 n
#188
b100100 +
b100100 Z
b100100 `
b100100 _
#189
b11000011 1
b11000011 @
b11000011 c
b1000 Q
b1000011100000000 P
b1000101100111 O
b1 V
b11000011 8
b11000011 T
b100001 4
b100001 6
b100001 A
b100001 D
b100001 G
b100001 J
b100001 M
b100001 S
b111 ]
b111 b
b100001000001100000011100001001 #
b100001000001100000011100001001 &
#190
b111000 a
b10100111 9
b10100111 K
b100001 ;
b100001 B
#191
b1000000 a
b10101000 7
b10101000 E
